{
  "99": "A",
  "0": "C",
  "197": "A",
  "393": "B",
  "295": "D",
  "100": "A",
  "198": "D",
  "1": "A",
  "296": "D",
  "394": "A",
  "199": "C",
  "101": "A",
  "2": "C",
  "297": "B",
  "395": "C",
  "200": "C",
  "3": "C",
  "298": "D",
  "102": "B",
  "201": "D",
  "396": "B",
  "299": "A",
  "4": "C",
  "202": "D",
  "103": "C",
  "300": "C",
  "397": "A",
  "5": "D",
  "203": "C",
  "6": "D",
  "301": "C",
  "104": "B",
  "398": "A",
  "204": "B",
  "7": "C",
  "302": "A",
  "105": "B",
  "399": "C",
  "303": "C",
  "8": "B",
  "205": "B",
  "304": "C",
  "9": "A",
  "106": "B",
  "400": "B",
  "206": "A",
  "10": "C",
  "305": "C",
  "401": "C",
  "207": "B",
  "306": "C",
  "107": "D",
  "11": "D",
  "402": "B",
  "208": "C",
  "108": "D",
  "307": "D",
  "12": "C",
  "209": "D",
  "308": "A",
  "109": "C",
  "13": "C",
  "403": "C",
  "309": "B",
  "110": "C",
  "210": "B",
  "404": "B",
  "14": "C",
  "111": "A",
  "310": "D",
  "211": "A",
  "405": "A",
  "15": "D",
  "311": "B",
  "112": "A",
  "406": "B",
  "212": "C",
  "312": "C",
  "16": "B",
  "213": "B",
  "113": "B",
  "313": "B",
  "407": "B",
  "17": "C",
  "214": "B",
  "314": "C",
  "215": "B",
  "408": "B",
  "114": "D",
  "315": "C",
  "18": "B",
  "316": "A",
  "409": "D",
  "19": "C",
  "115": "A",
  "216": "B",
  "317": "B",
  "410": "D",
  "20": "A",
  "318": "C",
  "217": "C",
  "411": "C",
  "116": "D",
  "319": "A",
  "21": "D",
  "218": "C",
  "117": "A",
  "412": "B",
  "219": "A",
  "22": "C",
  "118": "D",
  "320": "D",
  "413": "B",
  "220": "C",
  "321": "B",
  "414": "B",
  "23": "B",
  "415": "C",
  "221": "B",
  "24": "A",
  "119": "C",
  "322": "B",
  "416": "C",
  "222": "B",
  "25": "B",
  "323": "B",
  "223": "B",
  "26": "B",
  "417": "C",
  "324": "A",
  "120": "D",
  "224": "B",
  "418": "C",
  "27": "A",
  "325": "A",
  "419": "B",
  "326": "C",
  "121": "C",
  "225": "B",
  "28": "D",
  "420": "C",
  "226": "B",
  "327": "B",
  "29": "D",
  "421": "B",
  "328": "D",
  "30": "B",
  "227": "B",
  "122": "A",
  "329": "C",
  "422": "D",
  "31": "C",
  "228": "C",
  "229": "B",
  "32": "C",
  "123": "B",
  "330": "A",
  "423": "C",
  "230": "C",
  "331": "C",
  "124": "B",
  "33": "A",
  "424": "B",
  "332": "C",
  "231": "B",
  "34": "B",
  "125": "C",
  "425": "B",
  "232": "B",
  "333": "A",
  "35": "B",
  "334": "B",
  "233": "C",
  "426": "A",
  "36": "B",
  "234": "C",
  "126": "D",
  "335": "B",
  "37": "A",
  "336": "C",
  "235": "C",
  "427": "C",
  "337": "B",
  "127": "A",
  "236": "C",
  "428": "C",
  "338": "B",
  "38": "B",
  "237": "B",
  "128": "D",
  "429": "C",
  "339": "B",
  "39": "A",
  "430": "D",
  "238": "B",
  "129": "B",
  "40": "C",
  "340": "A",
  "239": "B",
  "41": "A",
  "130": "C",
  "341": "B",
  "240": "B",
  "42": "D",
  "342": "B",
  "241": "D",
  "431": "C",
  "43": "B",
  "131": "B",
  "343": "A",
  "242": "A",
  "44": "B",
  "344": "A",
  "243": "B",
  "432": "D",
  "45": "B",
  "132": "A",
  "433": "C",
  "345": "A",
  "244": "C",
  "46": "A",
  "133": "A",
  "434": "B",
  "346": "B",
  "245": "C",
  "47": "C",
  "435": "C",
  "246": "C",
  "134": "B",
  "347": "D",
  "48": "B",
  "436": "C",
  "247": "A",
  "348": "B",
  "135": "A",
  "49": "B",
  "248": "B",
  "349": "D",
  "437": "D",
  "50": "D",
  "249": "C",
  "136": "A",
  "350": "C",
  "51": "B",
  "438": "D",
  "351": "B",
  "352": "A",
  "250": "C",
  "52": "A",
  "439": "B",
  "353": "A",
  "137": "A",
  "251": "B",
  "53": "B",
  "440": "C",
  "354": "B",
  "441": "D",
  "54": "B",
  "138": "A",
  "252": "C",
  "55": "B",
  "355": "B",
  "253": "C",
  "442": "D",
  "56": "C",
  "139": "C",
  "254": "B",
  "443": "B",
  "356": "B",
  "140": "D",
  "57": "C",
  "444": "B",
  "357": "B",
  "255": "A",
  "58": "D",
  "445": "B",
  "256": "C",
  "358": "D",
  "59": "B",
  "141": "B",
  "446": "C",
  "257": "B",
  "60": "D",
  "142": "D",
  "359": "B",
  "61": "B",
  "258": "A",
  "143": "C",
  "360": "B",
  "447": "C",
  "62": "B",
  "259": "D",
  "144": "A",
  "361": "D",
  "63": "B",
  "448": "C",
  "145": "C",
  "449": "D",
  "64": "D",
  "362": "B",
  "260": "B",
  "450": "A",
  "261": "B",
  "363": "C",
  "65": "B",
  "146": "B",
  "66": "A",
  "451": "B",
  "67": "D",
  "262": "D",
  "364": "D",
  "147": "B",
  "68": "A",
  "452": "D",
  "453": "B",
  "263": "B",
  "365": "A",
  "69": "D",
  "148": "C",
  "454": "B",
  "366": "B",
  "264": "A",
  "149": "D",
  "70": "C",
  "367": "B",
  "455": "C",
  "71": "C",
  "150": "B",
  "368": "B",
  "456": "B",
  "265": "A",
  "369": "C",
  "72": "D",
  "457": "C",
  "151": "A",
  "73": "C",
  "266": "B",
  "152": "A",
  "74": "A",
  "370": "B",
  "267": "D",
  "458": "C",
  "75": "D",
  "371": "C",
  "459": "C",
  "153": "C",
  "268": "B",
  "76": "A",
  "372": "C",
  "460": "D",
  "154": "D",
  "373": "C",
  "269": "B",
  "77": "B",
  "155": "C",
  "374": "B",
  "461": "B",
  "78": "B",
  "270": "C",
  "375": "A",
  "462": "A",
  "271": "A",
  "79": "A",
  "156": "C",
  "376": "B",
  "463": "B",
  "464": "A",
  "377": "A",
  "80": "B",
  "378": "B",
  "272": "C",
  "81": "B",
  "465": "A",
  "379": "A",
  "273": "B",
  "82": "A",
  "466": "A",
  "157": "C",
  "380": "B",
  "274": "D",
  "158": "D",
  "381": "C",
  "467": "B",
  "83": "B",
  "275": "A",
  "382": "B",
  "159": "C",
  "468": "A",
  "84": "C",
  "276": "C",
  "469": "A",
  "85": "C",
  "277": "C",
  "470": "B",
  "160": "C",
  "383": "C",
  "384": "A",
  "471": "A",
  "472": "A",
  "473": "D",
  "86": "C",
  "278": "B",
  "161": "B",
  "385": "B",
  "279": "A",
  "87": "D",
  "162": "B",
  "88": "B",
  "474": "C",
  "386": "B",
  "280": "A",
  "89": "D",
  "475": "C",
  "281": "C",
  "387": "A",
  "90": "A",
  "163": "B",
  "282": "D",
  "388": "A",
  "476": "B",
  "283": "B",
  "164": "B",
  "477": "B",
  "91": "A",
  "389": "D",
  "478": "D",
  "479": "A",
  "284": "B",
  "480": "B",
  "165": "C",
  "390": "A",
  "285": "C",
  "481": "A",
  "391": "B",
  "286": "C",
  "92": "C",
  "166": "D",
  "482": "B",
  "392": "D",
  "483": "C",
  "167": "B",
  "287": "C",
  "93": "B",
  "484": "D",
  "288": "B",
  "94": "A",
  "168": "B",
  "485": "A",
  "95": "A",
  "289": "C",
  "169": "C",
  "96": "A",
  "486": "D",
  "290": "A",
  "97": "D",
  "170": "B",
  "487": "B",
  "291": "B",
  "98": "B",
  "488": "A",
  "292": "A",
  "293": "A",
  "489": "A",
  "171": "D",
  "294": "A",
  "490": "B",
  "172": "D",
  "173": "C",
  "174": "B",
  "175": "B",
  "176": "A",
  "177": "A",
  "178": "D",
  "179": "C",
  "180": "C",
  "181": "D",
  "182": "D",
  "183": "C",
  "184": "D",
  "185": "D",
  "186": "C",
  "187": "A",
  "188": "D",
  "189": "A",
  "190": "B",
  "191": "C",
  "192": "C",
  "193": "C",
  "194": "A",
  "195": "B",
  "196": "C"
}