{
  "7": "C",
  "21": "B",
  "24": "B",
  "31": "C",
  "50": "B",
  "56": "B",
  "75": "D",
  "82": "B",
  "89": "A",
  "108": "D",
  "126": "D",
  "136": "A",
  "145": "A",
  "152": "A",
  "159": "C",
  "178": "C",
  "187": "B",
  "195": "B",
  "210": "D",
  "218": "C",
  "245": "B",
  "253": "C",
  "264": "A",
  "282": "D",
  "310": "C",
  "323": "B",
  "341": "C",
  "372": "C",
  "403": "C",
  "425": "A",
  "453": "B",
  "477": "B",
  "2": "B",
  "33": "B",
  "43": "B",
  "54": "B",
  "87": "A",
  "94": "A",
  "112": "A",
  "125": "C",
  "134": "D",
  "143": "A",
  "169": "C",
  "194": "A",
  "225": "B",
  "241": "C",
  "260": "C",
  "281": "D",
  "303": "C",
  "325": "A",
  "351": "B",
  "379": "C",
  "399": "C",
  "419": "B",
  "438": "A",
  "463": "B",
  "488": "B",
  "5": "D",
  "17": "D",
  "32": "C",
  "60": "A",
  "100": "C",
  "131": "B",
  "151": "A",
  "168": "A",
  "183": "C",
  "203": "D",
  "227": "A",
  "252": "C",
  "271": "D",
  "295": "D",
  "319": "A",
  "345": "B",
  "375": "A",
  "401": "C",
  "422": "D",
  "446": "D",
  "487": "B"
}